face_recognition_system/__init__.py
face_recognition_system/face_recognition_system.py
face_recognitioniiti-0.1.7.dist-info/LICENSE
face_recognitioniiti-0.1.7.dist-info/METADATA
face_recognitioniiti-0.1.7.dist-info/WHEEL
face_recognitioniiti-0.1.7.dist-info/entry_points.txt
face_recognitioniiti-0.1.7.dist-info/top_level.txt
face_recognitioniiti-0.1.7.dist-info/RECORD
