Metadata-Version: 2.1
Name: face_recognitioniiti
Version: 0.1.7
Summary: A package that contains a Real-time Face Recognition System.
Home-page: https://github.com/Warlord-K/InterIIT-facerecognition
Author: Yatharth Gupta
Author-email: kkmvymayank@gmail.com
Classifier: Programming Language :: Python :: 3
Classifier: License :: OSI Approved :: MIT License
Classifier: Operating System :: OS Independent
Requires-Python: >=3.6
License-File: LICENSE
Requires-Dist: numpy
Requires-Dist: torch
Requires-Dist: protobuf
Requires-Dist: opencv-python
Requires-Dist: torchvision
Requires-Dist: ultralytics
Requires-Dist: arcFace
Provides-Extra: dev
